mozilla_version/__init__.py
mozilla_version/balrog.py
mozilla_version/errors.py
mozilla_version/fenix.py
mozilla_version/gecko.py
mozilla_version/ios.py
mozilla_version/maven.py
mozilla_version/mobile.py
mozilla_version/parser.py
mozilla_version/version.py
mozilla_version/test/__init__.py
mozilla_version/test/test_balrog.py
mozilla_version/test/test_default_imports.py
mozilla_version/test/test_errors.py
mozilla_version/test/test_fenix.py
mozilla_version/test/test_gecko.py
mozilla_version/test/test_ios.py
mozilla_version/test/test_maven.py
mozilla_version/test/test_mobile.py
mozilla_version/test/test_version.py
mozilla_version/test/integration/__init__.py
mozilla_version/test/integration/test_product_details.py
mozilla_version-5.0.0.dist-info/licenses/LICENSE
mozilla_version-5.0.0.dist-info/METADATA
mozilla_version-5.0.0.dist-info/WHEEL
mozilla_version-5.0.0.dist-info/top_level.txt
mozilla_version-5.0.0.dist-info/RECORD
